taskinity/__init__.py
taskinity/api.py
taskinity/api_client.py
taskinity/cli.py
taskinity/core/__init__.py
taskinity/core/taskinity_core.py
taskinity/core/taskinity_core_backup.py
taskinity/core/taskinity_core_fixed.py
taskinity/dashboard.py
taskinity/data_processors.py
taskinity/data_transformers.py
taskinity/examples.py
taskinity/execution_visualizer.py
taskinity/extensions/__init__.py
taskinity/extensions/code_converter.py
taskinity/extensions/mermaid_converter.py
taskinity/extensions/visualizer.py
taskinity/flow_dsl.py
taskinity/flow_scheduler.py
taskinity/flow_visualizer.py
taskinity/notification.py
taskinity/notification_service.py
taskinity/parallel_executor.py
taskinity/scheduler.py
taskinity/utils/__init__.py
taskinity/utils/benchmarks.py
taskinity/utils/env_loader.py
taskinity/utils/logging.py
taskinity/utils/performance.py
taskinity/utils/validation.py
taskinity/utils.py
taskinity-0.1.5.dist-info/LICENSE
taskinity-0.1.5.dist-info/METADATA
taskinity-0.1.5.dist-info/WHEEL
taskinity-0.1.5.dist-info/entry_points.txt
taskinity-0.1.5.dist-info/RECORD
