Metadata-Version: 2.3
Name: taskinity
Version: 0.1.5
Summary: Inteligentny Framework do Orkiestracji Zadań
License: Apache
Keywords: workflow,orchestration,task,automation,dsl
Author: Tom Sapletta
Author-email: info@taskinity.com
Requires-Python: >=3.8, !=2.7.*, !=3.0.*, !=3.1.*, !=3.2.*, !=3.3.*, !=3.4.*, !=3.5.*, !=3.6.*, !=3.7.*
Classifier: Development Status :: 4 - Beta
Classifier: Intended Audience :: Developers
Classifier: License :: OSI Approved :: Apache Software License
Classifier: License :: Other/Proprietary License
Classifier: Programming Language :: Python :: 3
Classifier: Programming Language :: Python :: 3.9
Classifier: Programming Language :: Python :: 3.10
Classifier: Programming Language :: Python :: 3.11
Classifier: Programming Language :: Python :: 3.12
Classifier: Programming Language :: Python :: 3.13
Classifier: Programming Language :: Python :: 3.8
Classifier: Topic :: Software Development :: Libraries :: Python Modules
Provides-Extra: all
Provides-Extra: db
Provides-Extra: nlp
Provides-Extra: web
Requires-Dist: fastapi (>=0.109.0,<0.110.0) ; extra == "web" or extra == "all"
Requires-Dist: loguru (>=0.7.0,<0.8.0)
Requires-Dist: nltk (>=3.8.0,<4.0.0) ; extra == "nlp" or extra == "all"
Requires-Dist: pandas (>=2.0.0,<3.0.0)
Requires-Dist: pydantic (>=2.0.0,<3.0.0)
Requires-Dist: requests (>=2.28.0,<3.0.0)
Requires-Dist: sqlalchemy (>=2.0.0,<3.0.0) ; extra == "db" or extra == "all"
Requires-Dist: streamlit (>=1.22.0,<2.0.0) ; extra == "web" or extra == "all"
Requires-Dist: uvicorn (>=0.27.0,<0.28.0) ; extra == "web" or extra == "all"
Project-URL: Repository, https://github.com/taskinity/python
